cml/__init__.py
cml/admin.py
cml/auth.py
cml/conf.py
cml/items.py
cml/models.py
cml/urls.py
cml/utils.py
cml/views.py
cml/management/__init__.py
cml/management/commands/__init__.py
cml/management/commands/cmlpipelines.py
cml/migrations/0001_initial.py
cml/migrations/__init__.py
cml/templates/cml/cml-pipelines.txt
django_cml_integr-0.1.0.dist-info/LICENSE
django_cml_integr-0.1.0.dist-info/METADATA
django_cml_integr-0.1.0.dist-info/WHEEL
django_cml_integr-0.1.0.dist-info/top_level.txt
django_cml_integr-0.1.0.dist-info/RECORD
