Metadata-Version: 2.1
Name: django-cml-integr
Version: 0.1.0
Summary: App for data exchange in CommerceML 2 standard..
Home-page: https://github.com/PrimeStr/django-cml-integr
Author: Maxim Golovin
Author-email: boss@primestr.ru
License: BSD License
Platform: UNKNOWN
Classifier: Environment :: Web Environment
Classifier: Framework :: Django
Classifier: Framework :: Django :: 3.0
Classifier: Intended Audience :: Developers
Classifier: License :: OSI Approved :: BSD License
Classifier: Operating System :: OS Independent
Classifier: Programming Language :: Python
Classifier: Programming Language :: Python :: 3.3
Classifier: Programming Language :: Python :: 3.4
Classifier: Programming Language :: Python :: 3.5
Classifier: Topic :: Internet :: WWW/HTTP
Classifier: Topic :: Internet :: WWW/HTTP :: Dynamic Content
Requires-Python: >3.3.0
License-File: LICENSE
Requires-Dist: Django (>=3.0)
Requires-Dist: django-appconf (>=1.0.1)
Requires-Dist: six (>=1.12.0)
